LICENSE
MANIFEST.in
README.md
setup.py
django_gtf.egg-info/PKG-INFO
django_gtf.egg-info/SOURCES.txt
django_gtf.egg-info/dependency_links.txt
django_gtf.egg-info/namespace_packages.txt
django_gtf.egg-info/requires.txt
django_gtf.egg-info/top_level.txt
gtf/__init__.py
gtf/middleware.py