Metadata-Version: 1.1
Name: django-gtf
Version: 0.1
Summary: Generit Template Finder Middleware for Django
Home-page: https://github.com/fusionbox/django-gtf
Author: Fusionbox programmers
Author-email: programmers@fusionbox.com
License: BSD
Keywords: django boilerplate
Platform: any
Classifier: Environment :: Web Environment
Classifier: Framework :: Django
Requires: six
